airflow/providers/siafi/__init__.py
airflow/providers/siafi/provider.yaml
airflow/providers/siafi/hooks/__init__.py
airflow/providers/siafi/hooks/siafi.py
build/lib/airflow/providers/siafi/__init__.py
build/lib/airflow/providers/siafi/hooks/__init__.py
build/lib/airflow/providers/siafi/hooks/siafi.py
build/lib/build/lib/airflow/providers/siafi/__init__.py
build/lib/build/lib/airflow/providers/siafi/hooks/__init__.py
build/lib/build/lib/airflow/providers/siafi/hooks/siafi.py
build/lib/build/lib/env/bin/rst2html.py
build/lib/build/lib/env/bin/rst2html4.py
build/lib/build/lib/env/bin/rst2html5.py
build/lib/build/lib/env/bin/rst2latex.py
build/lib/build/lib/env/bin/rst2man.py
build/lib/build/lib/env/bin/rst2odt.py
build/lib/build/lib/env/bin/rst2odt_prepstyles.py
build/lib/build/lib/env/bin/rst2pseudoxml.py
build/lib/build/lib/env/bin/rst2s5.py
build/lib/build/lib/env/bin/rst2xetex.py
build/lib/build/lib/env/bin/rst2xml.py
build/lib/build/lib/env/bin/rstpep2html.py
build/lib/env/bin/rst2html.py
build/lib/env/bin/rst2html4.py
build/lib/env/bin/rst2html5.py
build/lib/env/bin/rst2latex.py
build/lib/env/bin/rst2man.py
build/lib/env/bin/rst2odt.py
build/lib/env/bin/rst2odt_prepstyles.py
build/lib/env/bin/rst2pseudoxml.py
build/lib/env/bin/rst2s5.py
build/lib/env/bin/rst2xetex.py
build/lib/env/bin/rst2xml.py
build/lib/env/bin/rstpep2html.py
env/bin/rst2html.py
env/bin/rst2html4.py
env/bin/rst2html5.py
env/bin/rst2latex.py
env/bin/rst2man.py
env/bin/rst2odt.py
env/bin/rst2odt_prepstyles.py
env/bin/rst2pseudoxml.py
env/bin/rst2s5.py
env/bin/rst2xetex.py
env/bin/rst2xml.py
env/bin/rstpep2html.py
airflow_providers_siafi-2.0.3.dist-info/LICENSE.txt
airflow_providers_siafi-2.0.3.dist-info/METADATA
airflow_providers_siafi-2.0.3.dist-info/WHEEL
airflow_providers_siafi-2.0.3.dist-info/top_level.txt
airflow_providers_siafi-2.0.3.dist-info/RECORD
