Metadata-Version: 2.1
Name: airflow-providers-siafi
Version: 2.0.3
Summary: Provider para interações com o SIAFI e seus sistemas derivados
Home-page: https://github.com/CarlosAdp/airflow-providers-siafi
Author: Carlos Alberto Duarte Pinto
Author-email: carlos.adpinto@gmail.com
License: UNKNOWN
Download-URL: https://github.com/CarlosAdp/airflow-providers-siafi/tarball/v2.0.3
Keywords: airflow,siafi,administracao,governo
Platform: UNKNOWN
License-File: LICENSE.txt
Requires-Dist: apache-airflow
